pyclics_clustering/__init__.py
pyclics_clustering/hlc.py
pyclics_clustering-1.0.0.dist-info/METADATA
pyclics_clustering-1.0.0.dist-info/RECORD
pyclics_clustering-1.0.0.dist-info/WHEEL
pyclics_clustering-1.0.0.dist-info/entry_points.txt
pyclics_clustering-1.0.0.dist-info/top_level.txt
