Metadata-Version: 2.1
Name: pyclics-clustering
Version: 1.0.0
Summary: clustering algorithms for CLICS networks
Home-page: https://github.com/clics/pyclics-clustering
Author: Johann-Mattis List and Robert Forkel
Author-email: clics@shh.mpg.de
License: UNKNOWN
Platform: UNKNOWN
Classifier: Development Status :: 4 - Beta
Classifier: Intended Audience :: Science/Research
Classifier: Operating System :: OS Independent
Classifier: Programming Language :: Python :: 3
Classifier: Programming Language :: Python :: 3.5
Classifier: Programming Language :: Python :: 3.6
Classifier: Programming Language :: Python :: 3.7
Requires-Python: >=3.5
Provides-Extra: dev
Provides-Extra: test
Requires-Dist: attrs (>=18.2)
Requires-Dist: python-louvain
Requires-Dist: networkx
Requires-Dist: pyclics (>=2.0.0)
Provides-Extra: dev
Requires-Dist: tox; extra == 'dev'
Requires-Dist: flake8; extra == 'dev'
Requires-Dist: wheel; extra == 'dev'
Requires-Dist: twine; extra == 'dev'
Provides-Extra: test
Requires-Dist: mock; extra == 'test'
Requires-Dist: pytest (>=3.6); extra == 'test'
Requires-Dist: pytest-mock; extra == 'test'
Requires-Dist: pytest-cov; extra == 'test'
Requires-Dist: coverage (>=4.2); extra == 'test'
